etl_pipes/__init__.py
etl_pipes/actors/__init__.py
etl_pipes/actors/actor.py
etl_pipes/actors/actor_system.py
etl_pipes/actors/common/__init__.py
etl_pipes/actors/common/logging.py
etl_pipes/actors/common/types.py
etl_pipes/common/__init__.py
etl_pipes/common/utils/__init__.py
etl_pipes/common/utils/type_hints.py
etl_pipes/context.py
etl_pipes/domain/__init__.py
etl_pipes/domain/types.py
etl_pipes/pipes/__init__.py
etl_pipes/pipes/base_pipe.py
etl_pipes/pipes/broadcast_parallel.py
etl_pipes/pipes/map_reduce.py
etl_pipes/pipes/maybe.py
etl_pipes/pipes/parallel.py
etl_pipes/pipes/pipeline/__init__.py
etl_pipes/pipes/pipeline/exceptions.py
etl_pipes/pipes/pipeline/pipe_welding_validator.py
etl_pipes/pipes/pipeline/pipeline.py
etl_pipes/pipes/void.py
etl_pipes-0.8.12.dist-info/METADATA
etl_pipes-0.8.12.dist-info/WHEEL
etl_pipes-0.8.12.dist-info/RECORD
