Metadata-Version: 2.1
Name: etl-pipes
Version: 0.8.12
Summary: 
Author: Tikhon Zaikin
Author-email: th@thevhs.club
Requires-Python: >=3.11,<4.0
Classifier: Programming Language :: Python :: 3
Classifier: Programming Language :: Python :: 3.11
Requires-Dist: pip (>=23.2,<24.0)
